wsi_annotations_kit/__init__.py
wsi_annotations_kit/text_json_to_xml.py
wsi_annotations_kit/text_xml_to_json.py
wsi_annotations_kit/wsi_annotations_kit.py
wsi_annotations_kit-1.4.10.dist-info/LICENSE
wsi_annotations_kit-1.4.10.dist-info/METADATA
wsi_annotations_kit-1.4.10.dist-info/WHEEL
wsi_annotations_kit-1.4.10.dist-info/top_level.txt
wsi_annotations_kit-1.4.10.dist-info/RECORD
