Metadata-Version: 2.1
Name: wsi-annotations-kit
Version: 1.4.10
Summary: Utility functions for generating, saving, and converting annotation files
Home-page: https://github.com/spborder/wsi_annotations_kit
Author: Sam Border
Author-email: sam.border2256@gmail.com
Classifier: Programming Language :: Python :: 3
Classifier: License :: OSI Approved :: MIT License
Classifier: Operating System :: OS Independent
License-File: LICENSE
Requires-Dist: lxml >=4.9.2
Requires-Dist: geojson >=3.0.1
Requires-Dist: shapely >=2.0.1
Requires-Dist: tqdm
Requires-Dist: numpy >=1.20.0
Requires-Dist: uuid
Requires-Dist: scikit-image
